nonebot_plugin_honor-0.2.0.dist-info/METADATA
nonebot_plugin_honor-0.2.0.dist-info/WHEEL
nonebot_plugin_honor/__init__.py
nonebot_plugin_honor/constant.py
nonebot_plugin_honor/draw.py
nonebot_plugin_honor/main.py
nonebot_plugin_honor/model.py
nonebot_plugin_honor/utils.py
nonebot_plugin_honor-0.2.0.dist-info/RECORD
