Metadata-Version: 2.1
Name: nonebot-plugin-honor
Version: 0.2.0
Summary: 简易查询王者荣耀英雄胜率
Author-Email: forchannot <yy320206@gmail.com>
License: MIT
Requires-Python: >=3.8
Requires-Dist: nonebot-plugin-send-anything-anywhere>=0.5.0
Requires-Dist: nonebot2>=2.2.0
Requires-Dist: pillow>=10.2.0
Requires-Dist: pydantic<2
